Metadata-Version: 1.0
Name: elon-kindle
Version: 0.0.6
Summary: send to kindle
Home-page: https://github.com/elon
Author: elon
Author-email: elon@126.com
License: GPL Licence
Keywords: elon
Platform: any
